app.py
mseep_mcp_newrelic-0.1.4.dist-info/METADATA
mseep_mcp_newrelic-0.1.4.dist-info/WHEEL
mseep_mcp_newrelic-0.1.4.dist-info/top_level.txt
mseep_mcp_newrelic-0.1.4.dist-info/RECORD
